qingping_iot_mqtt/__about__.py
qingping_iot_mqtt/__init__.py
qingping_iot_mqtt/__main__.py
qingping_iot_mqtt/const.py
qingping_iot_mqtt/cli/__init__.py
qingping_iot_mqtt/cli/db.py
qingping_iot_mqtt/cli/mqtt.py
qingping_iot_mqtt/cli/vm.py
qingping_iot_mqtt/config/load.py
qingping_iot_mqtt/config/schema.py
qingping_iot_mqtt/device/device.py
qingping_iot_mqtt/protocols/base.py
qingping_iot_mqtt/protocols/common_spec.py
qingping_iot_mqtt/protocols/hex.py
qingping_iot_mqtt/protocols/hex_spec.py
qingping_iot_mqtt/protocols/json.py
qingping_iot_mqtt/protocols/json_spec.py
qingping_iot_mqtt-0.1.1.dist-info/METADATA
qingping_iot_mqtt-0.1.1.dist-info/WHEEL
qingping_iot_mqtt-0.1.1.dist-info/entry_points.txt
qingping_iot_mqtt-0.1.1.dist-info/licenses/LICENSE
qingping_iot_mqtt-0.1.1.dist-info/RECORD
