Metadata-Version: 2.4
Name: qingping-iot-mqtt
Version: 0.1.1
Summary: Python library and utilities for working with Qingping IoT MQTT protocols - JSON and binary ("HEX").
Project-URL: Documentation, https://github.com/danielskowronski/qingping-iot-mqtt#readme
Project-URL: Issues, https://github.com/danielskowronski/qingping-iot-mqtt/issues
Project-URL: Source, https://github.com/danielskowronski/qingping-iot-mqtt
Author-email: Daniel Skowroński <daniel@skowron.ski>
License-Expression: BSD-3-Clause
License-File: LICENSE
Keywords: iot,mqtt,qingping
Classifier: Development Status :: 4 - Beta
Classifier: Programming Language :: Python
Classifier: Programming Language :: Python :: 3.8
Classifier: Programming Language :: Python :: 3.9
Classifier: Programming Language :: Python :: 3.10
Classifier: Programming Language :: Python :: 3.11
Classifier: Programming Language :: Python :: 3.12
Classifier: Programming Language :: Python :: Implementation :: CPython
Classifier: Programming Language :: Python :: Implementation :: PyPy
Requires-Python: >=3.8
Requires-Dist: click~=8.3.1
Requires-Dist: coloredlogs~=15.0.1
Requires-Dist: paho-mqtt~=2.1.0
Requires-Dist: peewee~=3.18.3
Requires-Dist: pydantic~=2.12.4
Requires-Dist: pyyaml~=6.0.3
Requires-Dist: requests~=2.32.5
